pyweatherflow_forecast/__init__.py
pyweatherflow_forecast/const.py
pyweatherflow_forecast/data.py
pyweatherflow_forecast/wffcst_lib.py
pyweatherflow_forecast-1.2.0.dist-info/licenses/LICENSE
pyweatherflow_forecast-1.2.0.dist-info/METADATA
pyweatherflow_forecast-1.2.0.dist-info/WHEEL
pyweatherflow_forecast-1.2.0.dist-info/top_level.txt
pyweatherflow_forecast-1.2.0.dist-info/RECORD
