Metadata-Version: 2.4
Name: pyweatherflow-forecast
Version: 1.2.0
Summary: Gets the weather forecast data from WeatherFlow
Home-page: https://github.com/briis/pyweatherflow_forecast
Author: briis
Author-email: bjarne@briis.com
License: MIT
Classifier: Programming Language :: Python :: 3
Classifier: License :: OSI Approved :: MIT License
Classifier: Operating System :: OS Independent
Classifier: Development Status :: 4 - Beta
License-File: LICENSE
Dynamic: author
Dynamic: author-email
Dynamic: classifier
Dynamic: description
Dynamic: description-content-type
Dynamic: home-page
Dynamic: license
Dynamic: license-file
Dynamic: summary
